dev/CogSci19_MatchingPennies_TOM_data.csv
dev/fit_maximum_likelihood.py
dev/json_writer.py
docs/Makefile
docs/agent.rst
docs/conf.py
docs/index.rst
docs/installation.rst
docs/ktom_functions.rst
docs/make.bat
docs/payoffmatrix.rst
docs/plot.rst
docs/using-tomsup.rst
docs/utils.rst
docs/_static/favicon.ico
docs/_static/icon.png
img/icon.png
img/icon_black.png
img/icon_black2.png
papers/introducing_tomsup/large_tournament.py
papers/introducing_tomsup/parameter_estimation.py
papers/introducing_tomsup/comparison/VBA_behavior_comparison.m
papers/introducing_tomsup/comparison/VBA_behavior_comparison_helper.m
papers/introducing_tomsup/comparison/VBA_speed_comparison.m
papers/introducing_tomsup/comparison/tomsup_behaviour_comparison.py
papers/introducing_tomsup/comparison/tomsup_speed_comparison.py
papers/introducing_tomsup/experiment_analysis/.Rprofile
papers/introducing_tomsup/experiment_analysis/CogSci19_MatchingPennies_TOM_data.csv
papers/introducing_tomsup/experiment_analysis/CogSci19_MatchingPennies_TOM_data_updated.csv
papers/introducing_tomsup/experiment_analysis/analysis.Rmd
papers/introducing_tomsup/experiment_analysis/forced_choices.py
papers/introducing_tomsup/experiment_analysis/renv.lock
papers/introducing_tomsup/experiment_analysis/renv/activate.R
papers/introducing_tomsup/parameters_estimation/bias.png
papers/introducing_tomsup/parameters_estimation/parameter_estimation.Rmd
papers/introducing_tomsup/parameters_estimation/pk.png
papers/introducing_tomsup/parameters_estimation/temp.png
papers/introducing_tomsup/parameters_estimation/volatility.png
tomsup/__init__.py
tomsup/about.py
tomsup/agent.py
tomsup/agent_info.json
tomsup/ktom_functions.py
tomsup/payoffmatrix.py
tomsup/plot.py
tomsup/utils.py
tomsup/tests/__init__.py
tomsup/tests/test_agent.py
tomsup/tests/test_ktom_functions.py
tomsup/tests/test_payoffmatrix.py
tomsup/tests/test_tutorials/__init__.py
tomsup/tests/test_tutorials/test_creating_an_agent.py
tomsup/tests/test_tutorials/test_getting_started.py
tomsup-1.4.1.dist-info/licenses/LICENSE
tomsup-1.4.1.dist-info/METADATA
tomsup-1.4.1.dist-info/WHEEL
tomsup-1.4.1.dist-info/top_level.txt
tomsup-1.4.1.dist-info/RECORD
