Metadata-Version: 2.4
Name: tomsup
Version: 1.4.1
Summary: An implementation of game theory of mind in a agent based framework following the implementation of Devaine, et al. (2017).
Author: Peter T. Waade
Author-email: "Kenneth C. Enevoldsen" <kenevoldsen@pm.me>
License: Apache License 2.0
Project-URL: Homepage, https://github.com/KennethEnevoldsen/tomsup
Keywords: tom,theory-of-mind,game-theory
Classifier: Development Status :: 5 - Production/Stable
Classifier: Environment :: Console
Classifier: Intended Audience :: Developers
Classifier: Intended Audience :: Science/Research
Classifier: Topic :: Scientific/Engineering
Classifier: Topic :: Scientific/Engineering :: Artificial Intelligence
Classifier: Operating System :: POSIX :: Linux
Classifier: Operating System :: MacOS :: MacOS X
Classifier: Operating System :: Microsoft :: Windows
Classifier: Programming Language :: Python :: 3
Classifier: Programming Language :: Python :: 3.9
Classifier: Programming Language :: Python :: 3.10
Classifier: Programming Language :: Python :: 3.11
Classifier: Programming Language :: Python :: 3.12
Requires-Python: <3.13,>=3.9
License-File: LICENSE
Requires-Dist: importlib-metadata>=1.0; python_version < "3.8"
Requires-Dist: numpy>1.24.4
Requires-Dist: pandas>=1.2.3
Requires-Dist: scipy>=1.6.3
Requires-Dist: matplotlib>=3.4.2
Requires-Dist: seaborn>=0.11.1
Requires-Dist: joblib>=1.2.0
Requires-Dist: wasabi>=0.8.2
Dynamic: license-file
